edfi_api_client/__init__.py
edfi_api_client/edfi_client.py
edfi_api_client/edfi_endpoint.py
edfi_api_client/edfi_params.py
edfi_api_client/edfi_swagger.py
edfi_api_client/util.py
edfi_api_client-0.2.3.dist-info/LICENSE
edfi_api_client-0.2.3.dist-info/METADATA
edfi_api_client-0.2.3.dist-info/WHEEL
edfi_api_client-0.2.3.dist-info/top_level.txt
edfi_api_client-0.2.3.dist-info/RECORD
