Metadata-Version: 2.1
Name: edfi-api-client
Version: 0.2.3
Summary: Ed-Fi API client and tools
Home-page: https://github.com/edanalytics/edfi_api_client
Author: Erik Joranlien, Jay Kaiser
Author-email: ejoranlien@edanalytics.org, jkaiser@edanalytics.org
License: UNKNOWN
Platform: UNKNOWN
License-File: LICENSE
Requires-Dist: requests
